usql_conf/__init__.py
usql_conf/__main__.py
usql_conf/cli.py
usql_conf/py.typed
usql_conf-0.0.3.dist-info/LICENSE
usql_conf-0.0.3.dist-info/METADATA
usql_conf-0.0.3.dist-info/WHEEL
usql_conf-0.0.3.dist-info/entry_points.txt
usql_conf-0.0.3.dist-info/top_level.txt
usql_conf-0.0.3.dist-info/RECORD
