Metadata-Version: 2.1
Name: usql_conf
Version: 0.0.3
Summary: CLI for Managing SQL Connection Strings used in usql CLI
Home-page: https://github.com/jpy-git/usql_conf
Author: Joe Young
Author-email: josephyoung.jpy@gmail.com
License: MIT
Keywords: usql
Platform: UNKNOWN
Classifier: Development Status :: 3 - Alpha
Classifier: Environment :: Console
Classifier: Intended Audience :: Developers
Classifier: License :: OSI Approved :: MIT License
Classifier: Programming Language :: Python
Classifier: Programming Language :: Python :: 3
Classifier: Programming Language :: Python :: 3 :: Only
Classifier: Programming Language :: Python :: 3.6
Classifier: Programming Language :: Python :: 3.7
Classifier: Programming Language :: Python :: 3.8
Classifier: Programming Language :: Python :: 3.9
Classifier: Programming Language :: Python :: 3.10
Classifier: Programming Language :: Python :: Implementation :: CPython
Requires-Python: >=3.6
License-File: LICENSE
